MANIFEST.in
PULL_REQUEST_TEMPLATE.md
README.md
requirements.txt
setup.cfg
setup.py
examples/pt-wp-crawler.py
perftracker_cp_crawler/__init__.py
perftracker_cp_crawler/browser_base.py
perftracker_cp_crawler/browser_chrome.py
perftracker_cp_crawler/browser_firefox.py
perftracker_cp_crawler/browser_python.py
perftracker_cp_crawler/browser_webdriver.py
perftracker_cp_crawler/cp_crawler.py
perftracker_cp_crawler/cp_engine.py
perftracker_cp_crawler/html_report.py
perftracker_cp_crawler/httppool.py
perftracker_cp_crawler/httputils.py
perftracker_cp_crawler/page.py
perftracker_cp_crawler/utils.py
perftracker_cp_crawler/wpa_cp_engine.py
perftracker_cp_crawler.egg-info/PKG-INFO
perftracker_cp_crawler.egg-info/SOURCES.txt
perftracker_cp_crawler.egg-info/dependency_links.txt
perftracker_cp_crawler.egg-info/requires.txt
perftracker_cp_crawler.egg-info/top_level.txt