Metadata-Version: 2.1
Name: perftracker-cp-crawler
Version: 0.1.2
Summary: Python package with the perftracker control panels crawler
Home-page: http://www.perftracker.org
Author: perfguru87
Author-email: perfguru87@gmail.com
License: MIT License
Keywords: performance tests tools selenium webdriver perftracker client
Platform: UNKNOWN
Classifier: Development Status :: 4 - Beta
Classifier: Intended Audience :: Developers
Classifier: Topic :: Software Development :: Testing
Classifier: License :: OSI Approved :: MIT License
Classifier: Programming Language :: Python :: 2.6
Classifier: Programming Language :: Python :: 2.7
Classifier: Programming Language :: Python :: 3
Classifier: Programming Language :: Python :: 3.3
Classifier: Programming Language :: Python :: 3.4
Classifier: Programming Language :: Python :: 3.5
Provides-Extra: test
